clebs_puc_ia_csv_converter/__init__.py
clebs_puc_ia_csv_converter/converter.py
clebs_puc_ia_csv_converter-0.1.1.dist-info/entry_points.txt
clebs_puc_ia_csv_converter-0.1.1.dist-info/WHEEL
clebs_puc_ia_csv_converter-0.1.1.dist-info/METADATA
clebs_puc_ia_csv_converter-0.1.1.dist-info/RECORD
